Metadata-Version: 1.0
Name: dimakotelnikovvProject
Version: 0.0.1
Summary: My Package
Home-page: UNKNOWN
Author: Your Name
Author-email: dimakotelnikovv@yandex.ru
License: UNKNOWN
Platform: UNKNOWN
